activate_aiida/__init__.py
activate_aiida/parse_args.py
activate_aiida/read_config.py
activate_aiida-0.3.0.data/scripts/aiida-activate
activate_aiida-0.3.0.data/scripts/aiida-deactivate
activate_aiida-0.3.0.dist-info/LICENSE
activate_aiida-0.3.0.dist-info/METADATA
activate_aiida-0.3.0.dist-info/WHEEL
activate_aiida-0.3.0.dist-info/entry_points.txt
activate_aiida-0.3.0.dist-info/top_level.txt
activate_aiida-0.3.0.dist-info/zip-safe
activate_aiida-0.3.0.dist-info/RECORD
